langchain_pinecone/__init__.py
langchain_pinecone/_utilities.py
langchain_pinecone/embeddings.py
langchain_pinecone/py.typed
langchain_pinecone/vectorstores.py
gigachain_pinecone-0.1.3.dist-info/LICENSE
gigachain_pinecone-0.1.3.dist-info/METADATA
gigachain_pinecone-0.1.3.dist-info/WHEEL
gigachain_pinecone-0.1.3.dist-info/RECORD
